{
  "21": {
    "ok": true,
    "rowItems": {
      "0": "2101",
      "1": "21011",
      "2": "2102",
      "3": "21021",
      "4": "2103",
      "5": "21031",
      "6": "2104",
      "7": "21041",
      "8": "2107",
      "9": "21071",
      "10": "2113",
      "11": "21131",
      "12": "-"
    },
    "selects": [
      {
        "name": "",
        "opts": [
          "2101:2101|酶联免疫吸附试验（ELISA）",
          "2102:2102|放射免疫试验（RIA）",
          "2103:2103|间接免疫荧光试验（IFA）",
          "2104:2104|单向(环状)免疫扩散法(SRID)",
          "2105:2105|免疫透射比浊法(ITA)",
          "2106:2106|免疫散射比浊法（INA)",
          "2107:2107|乳胶凝集试验（LA）",
          "2108:2108|免疫渗滤层析试验",
          "2109:2109|快速血浆反应素环状卡片试验(RPR)",
          "2110:2110|不加热血清反应素试验(USR)",
          "2111:2111|螺旋体血球凝集试验(TPHA)",
          "2112:2112|甲苯胺红不加热血清试验(TRUST)",
          "2113:2113|明胶颗粒凝集试验(PA)",
          "2114:2114|荧光偏振免疫试验(FPIA)",
          "2115:2115|时间分辨荧光免疫试验（TR-FIA)",
          "2116:2116|化学发光免疫实验（CLIA）",
          "2117:2117|电化学发光免疫试验（ECLA)",
          "2118:2118|化学发光酶免疫试验（CLEIA）",
          "2119:2119|聚合酶链反应(PCR)",
          "2120:2120|逆转录-聚合酶链反应(RT-PCR)",
          "2121:2121|实时荧光PCR(定量)",
          "2123:2123|转录基于的放大系统(NASBA)",
          "2124:2124|连接酶链反应(LCR)",
          "2125:2125|链替代放大系统(SDA)",
          "2127:2127|bDNA信号放大系统(bDNA)",
          "2128:2128|免疫印记（包括westernblot和RIBA等）",
          "2129:2129|增强化学发光免疫试验",
          "2130:2130|PCR ELISA 定量",
          "2131:2131|PCR ELISA 定性",
          "2133:2133|PCR-反向定点杂交法",
          "2181:2181|透射比浊法",
          "2182:2182|速率散射比浊法",
          "2183:2183|微粒子酶免疫分析",
          "2184:2184|单向（环状）免疫扩散法",
          "2185:2185|散射比浊法（终点法）",
          "2186:2186|免疫印迹",
          "2187:2187|斑点法",
          "2188:2188|酶免疫分析",
          "2189:2189|扫描仪",
          "2190:2190|吖啶酯直接化学发光",
          "2191:2191|光激化学发光",
          "2192:2192|鲁米诺/异鲁米诺化学发光",
          "2199:2199|其它"
        ]
      },
      {
        "name": "",
        "opts": [
          "210000:210000|人眼判断",
          "211001:211001|AW I",
          "211002:211002|AW II",
          "211003:211003|Anthos 2001",
          "211004:211004|Anthos 2010 HT2改成",
          "211005:211005|Anthos HT3",
          "211006:211006|CliniBio 128",
          "211007:211007|CliniBio 128C",
          "211008:211008|DIAS+Vivace",
          "211009:211009|DV-990",
          "211010:211010|DigiScan",
          "211011:211011|EL-309",
          "211012:211012|EL-311",
          "211013:211013|EL-311s",
          "211014:211014|EL-312e",
          "211015:211015|EL-X800G",
          "211016:211016|EL-X800",
          "211017:211017|EL-X808",
          "211018:211018|FAME",
          "211019:211019|LP-400",
          "211020:211020|MR-4100",
          "211021:211021|MR-5000",
          "211022:211022|MRX",
          "211023:211023|MicroReader TM4",
          "211024:211024|Multiskan 352(MK352)",
          "211025:211025|Multiskan II(MK2)",
          "211026:211026|Multiskan III(MK3)",
          "211027:211027|Multiskan Mcc/340",
          "211028:211028|Multiskan Plus",
          "211029:211029|Organon Teknika Micr",
          "211031:211031|STAT FAX-2100",
          "211032:211032|Sigma 960",
          "211033:211033|Spectra Classic",
          "211035:211035|Spectra II",
          "211036:211036|Spectra III",
          "211037:211037|Wellscan",
          "211038:211038|伯乐3500",
          "211039:211039|伯乐3550",
          "211040:211040|伯乐450酶标仪",
          "211041:211041|伯乐550酶标仪",
          "211042:211042|伯乐Coda",
          "211044:211044|华东电子管厂GD-3021",
          "211045:211045|华东电子管厂GD-3022A",
          "211046:211046|Alisei全自动酶免分析仪",
          "211047:211047|普朗DNM9602酶标分析仪",
          "211048:211048|安图2010酶标仪",
          "211049:211049|Labsystem Multisckan Ascent",
          "211050:211050|TECAN Sunrise",
          "211051:211051|AT2000时间分辨检测系统",
          "211052:211052|伯乐680酶标仪",
          "211053:211053|罗氏 ELECSYS 2010",
          "211054:211054|变色龙酶免仪 TRITURUS",
          "211055:211055|宝灵曼ES-700全自动",
          "211056:211056|Anthos 340R",
          "211057:211057|Anthos 340RT",
          "211059:211059|AT-738半自动生化分析仪",
          "211060:211060|AT-838",
          "211061:211061|AFT212 FY1001",
          "211062:211062|ANSR",
          "211063:211063|ET-630G",
          "211064:211064|FG-2008G",
          "211065:211065|FJ-2003/50A",
          "211066:211066|FJ-2008",
          "211067:211067|FJ-2008G",
          "211068:211068|FJ-2008P",
          "211069:211069|FJ-2008PS",
          "211070:211070|FJ-2011",
          "211071:211071|FMJ-180",
          "211072:211072|FMJ-182",
          "211073:211073|FT-613",
          "211074:211074|FT-630G",
          "211075:211075|FT-646A",
          "211076:211076|GAMMA-C12",
          "211077:211077|GC-1200",
          "211078:211078|GC-400",
          "211079:211079|GC-911",
          "211080:211080|ISO-DATA",
          "211081:211081|SN-682",
          "211082:211082|SN-682B",
          "211083:211083|SN-682B2",
          "211084:211084|SN-695",
          "211085:211085|SN-695B",
          "211086:211086|TG-2003",
          "211087:211087|XH-6010",
          "211088:211088|贝克曼CX系列生化分析仪",
          "211089:211089|岛津CL系列生化分析仪",
          "211090:211090|日立 7060，7150，717",
          "211091:211091|意大利BT系列生化分析仪",
          "211092:211092|荷兰ISP系列生化分析仪",
          "211093:211093|Technicon RA50生化分析仪",
          "211094:211094|Technicon RA1000生化仪",
          "211095:211095|721或722型分光光度计",
          "211096:211096|HVK-60免疫比浊仪",
          "211097:211097|ASYS HITECH Gmbh",
          "211099:211099|罗氏 E170",
          "211100:211100|DENLEY DRAGON MK2",
          "211101:211101|DENLEY DRAGON MK3",
          "211102:211102|Bio-Rad iCycle",
          "211103:211103|Bio-Cell 2010",
          "211104:211104|Bio-Cell HT1",
          "211105:211105|Human",
          "211106:211106|Microplate Reader 318,318MC",
          "211107:211107|OPSYS MR CB-372",
          "211108:211108|Personal-LAB",
          "211109:211109|XD-711,711C",
          "211110:211110|XH-711",
          "211111:211111|RT-2100",
          "211112:211112|RT-2100C",
          "211113:211113|V-max",
          "211115:211115|上海新波",
          "211117:211117|Bio-RAD 680",
          "211118:211118|意大利 Alisei",
          "211119:211119|DNM-9602",
          "211120:211120|Emax",
          "211121:211121|BEP-2000",
          "213002:213002|雅培AXSYM 免疫分析仪",
          "213005:213005|Chiron ACS 180SE 全自动酶免分析系统",
          "213006:213006|强生OCD Vitros Eci",
          "213007:213007|雅培i2000/Alinity i",
          "213008:213008|亚斯特Personal LAB 全自动酶免分析仪",
          "213009:213009|亚斯特Nexgen Four 全自动酶免分析仪",
          "213010:213010|上海科华 ST-36W型酶标仪",
          "213019:213019|科美诊断chemclin600全自动化学发光仪",
          "213020:213020|科美诊断chemclin100半自动化学发光仪",
          "213021:213021|科美诊断chemclin1500全自动化学发光免疫分析仪",
          "215001:215001|雷杜RT-6000",
          "215002:215002|雷杜RT-6100",
          "215003:215003|罗氏 Cobas e 411",
          "215004:215004|罗氏 Cobas e 601",
          "215005:215005|HISCL-5000全自动免疫分析仪",
          "215006:215006|HISCL-800全自动免疫分析仪",
          "215007:215007|HISCL-2000i全自动免疫分析仪",
          "215008:215008|罗氏 Cobas e801",
          "217004:217004|OLYMPUS BX（BX50 BX60）显微镜",
          "217008:217008|OLYMPUS其他荧光显微镜",
          "217013:217013|NIKON Fluophoto显微镜",
          "217014:217014|NIKON其他荧光显微镜",
          "217018:217018|其他荧光显微镜",
          "218001:218001|ABI 2400 PCR 仪",
          "218002:218002|ABI 9600 PCR 仪",
          "218003:218003|ABI 9700 PCR 仪",
          "218004:218004|PTC-200 热循环仪",
          "218005:218005|PTC-100 热循环仪",
          "218011:218011|ABI 5700 荧光定量PCR仪",
          "218012:218012|ROCHE Lightcycler",
          "218013:218013|Bio-Rad iCycler",
          "218014:218014|Bio-Rad iCycler 480",
          "218019:218019|ABI 7700 荧光定量PCR仪",
          "218020:218020|ABI 7000 荧光定量PCR仪",
          "218021:218021|ABI 7900 荧光定量PCR仪",
          "218022:218022|COBAS AMPLICOR",
          "218023:218023|COBAS TaqMan",
          "218024:218024|ABI 7300 荧光定量PCR仪",
          "218025:218025|ABI 7500 荧光定量PCR仪",
          "218026:218026|Rotor Gene",
          "218027:218027|Line-Gene",
          "218028:218028|MJ Research Opticon II",
          "218029:218029|FTC 2000",
          "218030:218030|DA7600核酸扩增实时荧光检测系统",
          "218031:218031|科华FluoCycle 实时荧光定量PCR仪",
          "218032:218032|SLAN荧光定量PCR仪",
          "218099:218099|其它PCR仪",
          "218100:218100|医用核酸分子快速杂交仪HHM-2",
          "218101:218101|Luminex 100",
          "218102:218102|Luminex 200",
          "218103:218103|AM-1型全自动自身抗体分析仪",
          "218104:218104|EM-1型感染免疫分析仪",
          "218105:218105|Genelight 9800全自动医用PCR分析系统",
          "218106:218106|Genelight 2400全自动医用PCR分析系统",
          "218107:218107|伯乐CFX96实时定量PCR仪",
          "218108:218108|Liaison化学发光分析仪",
          "218109:218109|MiniVIDAS BLUE",
          "218110:218110|VIDAS 30 BLUE",
          "218111:218111|Auto lumiS 2000",
          "218112:218112|Auto lumiS 3000",
          "218113:218113|ADC ELISA",
          "218114:218114|迈克IS 1200全自动化学发光测定仪",
          "218115:218115|迈克i1000全自动化学发光测定仪",
          "218116:218116|迈克i3000全自动化学发光测定仪",
          "219010:219010|Beckman IMMAGE",
          "219020:219020|Dade Behring BNP",
          "219030:219030|Olympus AU2700",
          "219040:219040|欧蒙Scall",
          "219041:219041|欧蒙BX-51",
          "219042:219042|深圳迈瑞CL-900i/1000i/1200i/2000i/2200i/6000i/6200",
          "2190421:2190421|深圳迈瑞CL-8000i",
          "219043:219043|安图AutoLumo A2000",
          "219044:219044|安图AutoLumo A2000 Plus",
          "219045:219045|博奥赛斯（天津） Peteck 96-I",
          "219046:219046|博奥赛斯（天津） Axceed 200T/400T",
          "219047:219047|博奥赛斯（天津） Axceed 260/260X/260X1",
          "219048:219048|亚辉龙iFlash3000系列化学发光测定仪",
          "219049:219049|科美博阳LICA 500/LICA800/LICAsmart全自动化学发光仪",
          "219050:219050|日立",
          "219051:219051|四川沃文特LA3000/LA3000S",
          "219052:219052|厦门优迈科Caris200/Wan200/Wan100",
          "219053:219053|美康MS-i2280/3080",
          "219054:219054|中元汇吉EXI2400/8000",
          "219055:219055|深圳迈瑞 CL-9000i/9200i",
          "219056:219056|知微知微生物全自动核酸扩增分析仪（型号NAT-3000)",
          "219057:219057|知微生物全自动核酸扩增分析仪（型号NAT-3000 Pro-4)",
          "219058:219058|知微生物全自动核酸扩增分析仪（型号NAT-3000 Pro-8)",
          "219059:219059|知微生物全自动核酸扩增分析仪（型号NAT-3000 Pro-12)",
          "219060:219060|知微生物全自动核酸扩增分析仪（型号NAT-3000 Pro-16)",
          "219061:219061|新产业 Maglumi 全自动化学发光测定仪系列",
          "219999:219999|其它",
          "251003:251003|雷杜RT-2100C"
        ]
      },
      {
        "name": "",
        "opts": [
          "21001:21001|上海实业科华生物技术有限公司",
          "21002:21002|华美生物工程公司",
          "21003:21003|厦门新创科技有限公司",
          "21004:21004|上海市传染病医院诊断试剂研制中心",
          "21005:21005|北京科卫临床诊断试剂厂",
          "21006:21006|上海华泰生物工程实业有限公司",
          "21008:21008|北京美迪科生物技术有限责任公司（EIA)",
          "21010:21010|北京北方免疫试剂研究所(EIA)",
          "21011:21011|山东维坊3V诊断技术公司（EIA)",
          "21013:21013|美国贝克曼公司",
          "21015:21015|北京北方生物技术研究所(RIA)",
          "21016:21016|华大GBI生物技术(北京)有限公司",
          "21017:21017|美国万华普曼公司",
          "21018:21018|美国雅培公司（AXSYM)",
          "21019:21019|美国HELIX公司",
          "21020:21020|强生ORTHO 有限公司（ECI）",
          "21021:21021|生物梅里埃",
          "21022:21022|荷兰阿克苏诺贝尔公司",
          "21023:21023|法国赛诺菲公司",
          "21024:21024|上海荣盛生物技术有限公司",
          "21025:21025|美国GENBIO公司",
          "21027:21027|德国欧润",
          "21028:21028|德国埃天郎生物制品有限公司",
          "21029:21029|美国Trinity公司",
          "21030:21030|美国hope",
          "21031:21031|郑州安图绿科生物工程有限公司",
          "21032:21032|深圳华康生物工程有限公司",
          "21033:21033|上海复星实业股份有限公司",
          "21034:21034|天津新传生物技术有限公司",
          "21035:21035|天津普生生物技术有限公司",
          "21036:21036|山东维坊3V生物工程有限公司（RIA）",
          "21037:21037|深圳月亮湾生物工程有限公司",
          "21038:21038|广东中山生物工程公司",
          "21043:21043|丽珠集团公司丽珠试剂厂",
          "21044:21044|福盈生物工程有限公司",
          "21046:21046|北京金豪制药股份有限公司",
          "21050:21050|北京现代高达生物技术有限责任公司",
          "21063:21063|北京新兴四寰生物技术有限公司",
          "21064:21064|深圳迈瑞",
          "21078:21078|达安基因诊断中心",
          "21079:21079|美国BIOCHECK公司",
          "21080:21080|上海复星医学科技发展有限公司（PCR）",
          "21081:21081|北京万泰生物药业有限公司",
          "21082:21082|罗氏（ROCHE）投资有限公司",
          "21083:21083|厦门安普利生物工程公司",
          "21086:21086|上海申友生物技术有限责任公司",
          "21097:21097|深圳匹基生物技术有限公司",
          "21098:21098|广东万孚",
          "21099:21099|欧蒙实验免疫制品有限公司",
          "21105:21105|兰州蓝十字生物技术有限公司",
          "21106:21106|Labsystems公司",
          "21107:21107|意大利索林（SORIN)公司",
          "21108:21108|北京优耐特生物医学有限公司",
          "21109:21109|上海飞龙医用诊断用品公司",
          "21133:21133|北京协和医院",
          "21138:21138|北京金伟凯医学生物技术有限公司",
          "21143:21143|艾康生物技术（杭州）有限公司",
          "21144:21144|苏州新波生物技术有限公司",
          "21147:21147|美国雅培公司（i2000/Alinity i）",
          "21161:21161|湖南圣湘生物科技有限公司",
          "21162:21162|威海威高生物科技有限公司",
          "21163:21163|北京源德生物医学工程有限公司",
          "21164:21164|上海之江生物科技有限公司",
          "21175:21175|科美诊断技术股份有限公司",
          "21176:21176|日本希森美康",
          "21177:21177|深圳市亚辉龙生物科技股份有限公司(化学发光)",
          "21192:21192|北京雅康博生物科技有限公司",
          "21193:21193|郑州安图生物工程股份有限公司",
          "21901:21901|DADE",
          "21902:21902|朗道",
          "21903:21903|首医",
          "21904:21904|天津博奥赛斯",
          "21905:21905|科美博阳诊断技术技术（上海）有限公司",
          "21906:21906|四川沃文特生物技术有限公司",
          "21907:21907|厦门万泰凯瑞生物技术有限公司",
          "21908:21908|美康生物",
          "21909:21909|中元汇吉",
          "21910:21910|知微生物（北京）医疗科技有限公司",
          "21911:21911|深圳新产业",
          "21999:21999|其它"
        ]
      },
      {
        "name": "",
        "opts": [
          "21001:21001|上海实业科华生物技术有限公司",
          "21002:21002|华美生物工程公司",
          "21003:21003|厦门新创科技有限公司",
          "21004:21004|上海市传染病医院诊断试剂研制中心",
          "21005:21005|北京科卫临床诊断试剂厂",
          "21006:21006|上海华泰生物工程实业有限公司",
          "21008:21008|北京美迪科生物技术有限责任公司（EIA)",
          "21010:21010|北京北方免疫试剂研究所(EIA)",
          "21011:21011|山东维坊3V诊断技术公司（EIA)",
          "21013:21013|美国贝克曼公司",
          "21015:21015|北京北方生物技术研究所(RIA)",
          "21016:21016|华大GBI生物技术(北京)有限公司",
          "21017:21017|美国万华普曼公司",
          "21018:21018|美国雅培公司（AXSYM)",
          "21019:21019|美国HELIX公司",
          "21020:21020|强生ORTHO 有限公司（ECI）",
          "21021:21021|生物梅里埃",
          "21022:21022|荷兰阿克苏诺贝尔公司",
          "21023:21023|法国赛诺菲公司",
          "21024:21024|上海荣盛生物技术有限公司",
          "21025:21025|美国GENBIO公司",
          "21027:21027|德国欧润",
          "21028:21028|德国埃天郎生物制品有限公司",
          "21029:21029|美国Trinity公司",
          "21030:21030|美国hope",
          "21031:21031|郑州安图绿科生物工程有限公司",
          "21032:21032|深圳华康生物工程有限公司",
          "21033:21033|上海复星实业股份有限公司",
          "21034:21034|天津新传生物技术有限公司",
          "21035:21035|天津普生生物技术有限公司",
          "21036:21036|山东维坊3V生物工程有限公司（RIA）",
          "21037:21037|深圳月亮湾生物工程有限公司",
          "21038:21038|广东中山生物工程公司",
          "21043:21043|丽珠集团公司丽珠试剂厂",
          "21044:21044|福盈生物工程有限公司",
          "21046:21046|北京金豪制药股份有限公司",
          "21050:21050|北京现代高达生物技术有限责任公司",
          "21063:21063|北京新兴四寰生物技术有限公司",
          "21064:21064|深圳迈瑞",
          "21078:21078|达安基因诊断中心",
          "21079:21079|美国BIOCHECK公司",
          "21080:21080|上海复星医学科技发展有限公司（PCR）",
          "21081:21081|北京万泰生物药业有限公司",
          "21082:21082|罗氏（ROCHE）投资有限公司",
          "21083:21083|厦门安普利生物工程公司",
          "21086:21086|上海申友生物技术有限责任公司",
          "21097:21097|深圳匹基生物技术有限公司",
          "21098:21098|广东万孚",
          "21099:21099|欧蒙实验免疫制品有限公司",
          "21105:21105|兰州蓝十字生物技术有限公司",
          "21106:21106|Labsystems公司",
          "21107:21107|意大利索林（SORIN)公司",
          "21108:21108|北京优耐特生物医学有限公司",
          "21109:21109|上海飞龙医用诊断用品公司",
          "21133:21133|北京协和医院",
          "21138:21138|北京金伟凯医学生物技术有限公司",
          "21143:21143|艾康生物技术（杭州）有限公司",
          "21144:21144|苏州新波生物技术有限公司",
          "21147:21147|美国雅培公司（i2000/Alinity i）",
          "21161:21161|湖南圣湘生物科技有限公司",
          "21162:21162|威海威高生物科技有限公司",
          "21163:21163|北京源德生物医学工程有限公司",
          "21164:21164|上海之江生物科技有限公司",
          "21175:21175|科美诊断技术股份有限公司",
          "21176:21176|日本希森美康",
          "21177:21177|深圳市亚辉龙生物科技股份有限公司(化学发光)",
          "21192:21192|北京雅康博生物科技有限公司",
          "21193:21193|郑州安图生物工程股份有限公司",
          "21901:21901|DADE",
          "21902:21902|朗道",
          "21903:21903|首医",
          "21904:21904|天津博奥赛斯",
          "21905:21905|科美博阳诊断技术技术（上海）有限公司",
          "21906:21906|四川沃文特生物技术有限公司",
          "21907:21907|厦门万泰凯瑞生物技术有限公司",
          "21908:21908|美康生物",
          "21909:21909|中元汇吉",
          "21910:21910|知微生物（北京）医疗科技有限公司",
          "21911:21911|深圳新产业",
          "21999:21999|其它"
        ]
      }
    ],
    "headers": []
  },
  "86": {
    "ok": true,
    "rowItems": {
      "0": "8601",
      "1": "86011",
      "2": "8602",
      "3": "86021",
      "4": "8603",
      "5": "86031",
      "6": "-"
    },
    "selects": [
      {
        "name": "",
        "opts": [
          "2101:2101|酶联免疫吸附试验（ELISA）",
          "2102:2102|放射免疫试验（RIA）",
          "2103:2103|间接免疫荧光试验（IFA）",
          "2104:2104|单向(环状)免疫扩散法(SRID)",
          "2105:2105|免疫透射比浊法(ITA)",
          "2106:2106|免疫散射比浊法（INA)",
          "2107:2107|乳胶凝集试验（LA）",
          "2108:2108|免疫渗滤层析试验",
          "2109:2109|快速血浆反应素环状卡片试验(RPR)",
          "2110:2110|不加热血清反应素试验(USR)",
          "2111:2111|螺旋体血球凝集试验(TPHA)",
          "2112:2112|甲苯胺红不加热血清试验(TRUST)",
          "2113:2113|明胶颗粒凝集试验(PA)",
          "2114:2114|荧光偏振免疫试验(FPIA)",
          "2115:2115|时间分辨荧光免疫试验（TR-FIA)",
          "2116:2116|化学发光免疫实验（CLIA）",
          "2117:2117|电化学发光免疫试验（ECLA)",
          "2118:2118|化学发光酶免疫试验（CLEIA）",
          "2119:2119|聚合酶链反应(PCR)",
          "2120:2120|逆转录-聚合酶链反应(RT-PCR)",
          "2121:2121|实时荧光PCR(定量)",
          "2123:2123|转录基于的放大系统(NASBA)",
          "2124:2124|连接酶链反应(LCR)",
          "2125:2125|链替代放大系统(SDA)",
          "2127:2127|bDNA信号放大系统(bDNA)",
          "2128:2128|免疫印记（包括westernblot和RIBA等）",
          "2129:2129|增强化学发光免疫试验",
          "2130:2130|PCR ELISA 定量",
          "2131:2131|PCR ELISA 定性",
          "2133:2133|PCR-反向定点杂交法",
          "2181:2181|透射比浊法",
          "2182:2182|速率散射比浊法",
          "2183:2183|微粒子酶免疫分析",
          "2184:2184|单向（环状）免疫扩散法",
          "2185:2185|散射比浊法（终点法）",
          "2186:2186|免疫印迹",
          "2187:2187|斑点法",
          "2188:2188|酶免疫分析",
          "2189:2189|扫描仪",
          "2190:2190|吖啶酯直接化学发光",
          "2191:2191|光激化学发光",
          "2192:2192|鲁米诺/异鲁米诺化学发光",
          "2199:2199|其它"
        ]
      },
      {
        "name": "",
        "opts": [
          "210000:210000|人眼判断",
          "211001:211001|AW I",
          "211002:211002|AW II",
          "211003:211003|Anthos 2001",
          "211004:211004|Anthos 2010 HT2改成",
          "211005:211005|Anthos HT3",
          "211006:211006|CliniBio 128",
          "211007:211007|CliniBio 128C",
          "211008:211008|DIAS+Vivace",
          "211009:211009|DV-990",
          "211010:211010|DigiScan",
          "211011:211011|EL-309",
          "211012:211012|EL-311",
          "211013:211013|EL-311s",
          "211014:211014|EL-312e",
          "211015:211015|EL-X800G",
          "211016:211016|EL-X800",
          "211017:211017|EL-X808",
          "211018:211018|FAME",
          "211019:211019|LP-400",
          "211020:211020|MR-4100",
          "211021:211021|MR-5000",
          "211022:211022|MRX",
          "211023:211023|MicroReader TM4",
          "211024:211024|Multiskan 352(MK352)",
          "211025:211025|Multiskan II(MK2)",
          "211026:211026|Multiskan III(MK3)",
          "211027:211027|Multiskan Mcc/340",
          "211028:211028|Multiskan Plus",
          "211029:211029|Organon Teknika Micr",
          "211031:211031|STAT FAX-2100",
          "211032:211032|Sigma 960",
          "211033:211033|Spectra Classic",
          "211035:211035|Spectra II",
          "211036:211036|Spectra III",
          "211037:211037|Wellscan",
          "211038:211038|伯乐3500",
          "211039:211039|伯乐3550",
          "211040:211040|伯乐450酶标仪",
          "211041:211041|伯乐550酶标仪",
          "211042:211042|伯乐Coda",
          "211044:211044|华东电子管厂GD-3021",
          "211045:211045|华东电子管厂GD-3022A",
          "211046:211046|Alisei全自动酶免分析仪",
          "211047:211047|普朗DNM9602酶标分析仪",
          "211048:211048|安图2010酶标仪",
          "211049:211049|Labsystem Multisckan Ascent",
          "211050:211050|TECAN Sunrise",
          "211051:211051|AT2000时间分辨检测系统",
          "211052:211052|伯乐680酶标仪",
          "211053:211053|罗氏 ELECSYS 2010",
          "211054:211054|变色龙酶免仪 TRITURUS",
          "211055:211055|宝灵曼ES-700全自动",
          "211056:211056|Anthos 340R",
          "211057:211057|Anthos 340RT",
          "211059:211059|AT-738半自动生化分析仪",
          "211060:211060|AT-838",
          "211061:211061|AFT212 FY1001",
          "211062:211062|ANSR",
          "211063:211063|ET-630G",
          "211064:211064|FG-2008G",
          "211065:211065|FJ-2003/50A",
          "211066:211066|FJ-2008",
          "211067:211067|FJ-2008G",
          "211068:211068|FJ-2008P",
          "211069:211069|FJ-2008PS",
          "211070:211070|FJ-2011",
          "211071:211071|FMJ-180",
          "211072:211072|FMJ-182",
          "211073:211073|FT-613",
          "211074:211074|FT-630G",
          "211075:211075|FT-646A",
          "211076:211076|GAMMA-C12",
          "211077:211077|GC-1200",
          "211078:211078|GC-400",
          "211079:211079|GC-911",
          "211080:211080|ISO-DATA",
          "211081:211081|SN-682",
          "211082:211082|SN-682B",
          "211083:211083|SN-682B2",
          "211084:211084|SN-695",
          "211085:211085|SN-695B",
          "211086:211086|TG-2003",
          "211087:211087|XH-6010",
          "211088:211088|贝克曼CX系列生化分析仪",
          "211089:211089|岛津CL系列生化分析仪",
          "211090:211090|日立 7060，7150，717",
          "211091:211091|意大利BT系列生化分析仪",
          "211092:211092|荷兰ISP系列生化分析仪",
          "211093:211093|Technicon RA50生化分析仪",
          "211094:211094|Technicon RA1000生化仪",
          "211095:211095|721或722型分光光度计",
          "211096:211096|HVK-60免疫比浊仪",
          "211097:211097|ASYS HITECH Gmbh",
          "211099:211099|罗氏 E170",
          "211100:211100|DENLEY DRAGON MK2",
          "211101:211101|DENLEY DRAGON MK3",
          "211102:211102|Bio-Rad iCycle",
          "211103:211103|Bio-Cell 2010",
          "211104:211104|Bio-Cell HT1",
          "211105:211105|Human",
          "211106:211106|Microplate Reader 318,318MC",
          "211107:211107|OPSYS MR CB-372",
          "211108:211108|Personal-LAB",
          "211109:211109|XD-711,711C",
          "211110:211110|XH-711",
          "211111:211111|RT-2100",
          "211112:211112|RT-2100C",
          "211113:211113|V-max",
          "211115:211115|上海新波",
          "211117:211117|Bio-RAD 680",
          "211118:211118|意大利 Alisei",
          "211119:211119|DNM-9602",
          "211120:211120|Emax",
          "211121:211121|BEP-2000",
          "213002:213002|雅培AXSYM 免疫分析仪",
          "213005:213005|Chiron ACS 180SE 全自动酶免分析系统",
          "213006:213006|强生OCD Vitros Eci",
          "213007:213007|雅培i2000/Alinity i",
          "213008:213008|亚斯特Personal LAB 全自动酶免分析仪",
          "213009:213009|亚斯特Nexgen Four 全自动酶免分析仪",
          "213010:213010|上海科华 ST-36W型酶标仪",
          "213019:213019|科美诊断chemclin600全自动化学发光仪",
          "213020:213020|科美诊断chemclin100半自动化学发光仪",
          "213021:213021|科美诊断chemclin1500全自动化学发光免疫分析仪",
          "215001:215001|雷杜RT-6000",
          "215002:215002|雷杜RT-6100",
          "215003:215003|罗氏 Cobas e 411",
          "215004:215004|罗氏 Cobas e 601",
          "215005:215005|HISCL-5000全自动免疫分析仪",
          "215006:215006|HISCL-800全自动免疫分析仪",
          "215007:215007|HISCL-2000i全自动免疫分析仪",
          "215008:215008|罗氏 Cobas e801",
          "217004:217004|OLYMPUS BX（BX50 BX60）显微镜",
          "217008:217008|OLYMPUS其他荧光显微镜",
          "217013:217013|NIKON Fluophoto显微镜",
          "217014:217014|NIKON其他荧光显微镜",
          "217018:217018|其他荧光显微镜",
          "218001:218001|ABI 2400 PCR 仪",
          "218002:218002|ABI 9600 PCR 仪",
          "218003:218003|ABI 9700 PCR 仪",
          "218004:218004|PTC-200 热循环仪",
          "218005:218005|PTC-100 热循环仪",
          "218011:218011|ABI 5700 荧光定量PCR仪",
          "218012:218012|ROCHE Lightcycler",
          "218013:218013|Bio-Rad iCycler",
          "218014:218014|Bio-Rad iCycler 480",
          "218019:218019|ABI 7700 荧光定量PCR仪",
          "218020:218020|ABI 7000 荧光定量PCR仪",
          "218021:218021|ABI 7900 荧光定量PCR仪",
          "218022:218022|COBAS AMPLICOR",
          "218023:218023|COBAS TaqMan",
          "218024:218024|ABI 7300 荧光定量PCR仪",
          "218025:218025|ABI 7500 荧光定量PCR仪",
          "218026:218026|Rotor Gene",
          "218027:218027|Line-Gene",
          "218028:218028|MJ Research Opticon II",
          "218029:218029|FTC 2000",
          "218030:218030|DA7600核酸扩增实时荧光检测系统",
          "218031:218031|科华FluoCycle 实时荧光定量PCR仪",
          "218032:218032|SLAN荧光定量PCR仪",
          "218099:218099|其它PCR仪",
          "218100:218100|医用核酸分子快速杂交仪HHM-2",
          "218101:218101|Luminex 100",
          "218102:218102|Luminex 200",
          "218103:218103|AM-1型全自动自身抗体分析仪",
          "218104:218104|EM-1型感染免疫分析仪",
          "218105:218105|Genelight 9800全自动医用PCR分析系统",
          "218106:218106|Genelight 2400全自动医用PCR分析系统",
          "218107:218107|伯乐CFX96实时定量PCR仪",
          "218108:218108|Liaison化学发光分析仪",
          "218109:218109|MiniVIDAS BLUE",
          "218110:218110|VIDAS 30 BLUE",
          "218111:218111|Auto lumiS 2000",
          "218112:218112|Auto lumiS 3000",
          "218113:218113|ADC ELISA",
          "218114:218114|迈克IS 1200全自动化学发光测定仪",
          "218115:218115|迈克i1000全自动化学发光测定仪",
          "218116:218116|迈克i3000全自动化学发光测定仪",
          "219010:219010|Beckman IMMAGE",
          "219020:219020|Dade Behring BNP",
          "219030:219030|Olympus AU2700",
          "219040:219040|欧蒙Scall",
          "219041:219041|欧蒙BX-51",
          "219042:219042|深圳迈瑞CL-900i/1000i/1200i/2000i/2200i/6000i/6200",
          "2190421:2190421|深圳迈瑞CL-8000i",
          "219043:219043|安图AutoLumo A2000",
          "219044:219044|安图AutoLumo A2000 Plus",
          "219045:219045|博奥赛斯（天津） Peteck 96-I",
          "219046:219046|博奥赛斯（天津） Axceed 200T/400T",
          "219047:219047|博奥赛斯（天津） Axceed 260/260X/260X1",
          "219048:219048|亚辉龙iFlash3000系列化学发光测定仪",
          "219049:219049|科美博阳LICA 500/LICA800/LICAsmart全自动化学发光仪",
          "219050:219050|日立",
          "219051:219051|四川沃文特LA3000/LA3000S",
          "219052:219052|厦门优迈科Caris200/Wan200/Wan100",
          "219053:219053|美康MS-i2280/3080",
          "219054:219054|中元汇吉EXI2400/8000",
          "219055:219055|深圳迈瑞 CL-9000i/9200i",
          "219056:219056|知微知微生物全自动核酸扩增分析仪（型号NAT-3000)",
          "219057:219057|知微生物全自动核酸扩增分析仪（型号NAT-3000 Pro-4)",
          "219058:219058|知微生物全自动核酸扩增分析仪（型号NAT-3000 Pro-8)",
          "219059:219059|知微生物全自动核酸扩增分析仪（型号NAT-3000 Pro-12)",
          "219060:219060|知微生物全自动核酸扩增分析仪（型号NAT-3000 Pro-16)",
          "219061:219061|新产业 Maglumi 全自动化学发光测定仪系列",
          "219999:219999|其它",
          "251003:251003|雷杜RT-2100C"
        ]
      },
      {
        "name": "",
        "opts": [
          "21001:21001|上海实业科华生物技术有限公司",
          "21002:21002|华美生物工程公司",
          "21003:21003|厦门新创科技有限公司",
          "21004:21004|上海市传染病医院诊断试剂研制中心",
          "21005:21005|北京科卫临床诊断试剂厂",
          "21006:21006|上海华泰生物工程实业有限公司",
          "21008:21008|北京美迪科生物技术有限责任公司（EIA)",
          "21010:21010|北京北方免疫试剂研究所(EIA)",
          "21011:21011|山东维坊3V诊断技术公司（EIA)",
          "21013:21013|美国贝克曼公司",
          "21015:21015|北京北方生物技术研究所(RIA)",
          "21016:21016|华大GBI生物技术(北京)有限公司",
          "21017:21017|美国万华普曼公司",
          "21018:21018|美国雅培公司（AXSYM)",
          "21019:21019|美国HELIX公司",
          "21020:21020|强生ORTHO 有限公司（ECI）",
          "21021:21021|生物梅里埃",
          "21022:21022|荷兰阿克苏诺贝尔公司",
          "21023:21023|法国赛诺菲公司",
          "21024:21024|上海荣盛生物技术有限公司",
          "21025:21025|美国GENBIO公司",
          "21027:21027|德国欧润",
          "21028:21028|德国埃天郎生物制品有限公司",
          "21029:21029|美国Trinity公司",
          "21030:21030|美国hope",
          "21031:21031|郑州安图绿科生物工程有限公司",
          "21032:21032|深圳华康生物工程有限公司",
          "21033:21033|上海复星实业股份有限公司",
          "21034:21034|天津新传生物技术有限公司",
          "21035:21035|天津普生生物技术有限公司",
          "21036:21036|山东维坊3V生物工程有限公司（RIA）",
          "21037:21037|深圳月亮湾生物工程有限公司",
          "21038:21038|广东中山生物工程公司",
          "21043:21043|丽珠集团公司丽珠试剂厂",
          "21044:21044|福盈生物工程有限公司",
          "21046:21046|北京金豪制药股份有限公司",
          "21050:21050|北京现代高达生物技术有限责任公司",
          "21063:21063|北京新兴四寰生物技术有限公司",
          "21064:21064|深圳迈瑞",
          "21078:21078|达安基因诊断中心",
          "21079:21079|美国BIOCHECK公司",
          "21080:21080|上海复星医学科技发展有限公司（PCR）",
          "21081:21081|北京万泰生物药业有限公司",
          "21082:21082|罗氏（ROCHE）投资有限公司",
          "21083:21083|厦门安普利生物工程公司",
          "21086:21086|上海申友生物技术有限责任公司",
          "21097:21097|深圳匹基生物技术有限公司",
          "21098:21098|广东万孚",
          "21099:21099|欧蒙实验免疫制品有限公司",
          "21105:21105|兰州蓝十字生物技术有限公司",
          "21106:21106|Labsystems公司",
          "21107:21107|意大利索林（SORIN)公司",
          "21108:21108|北京优耐特生物医学有限公司",
          "21109:21109|上海飞龙医用诊断用品公司",
          "21133:21133|北京协和医院",
          "21138:21138|北京金伟凯医学生物技术有限公司",
          "21143:21143|艾康生物技术（杭州）有限公司",
          "21144:21144|苏州新波生物技术有限公司",
          "21147:21147|美国雅培公司（i2000/Alinity i）",
          "21161:21161|湖南圣湘生物科技有限公司",
          "21162:21162|威海威高生物科技有限公司",
          "21163:21163|北京源德生物医学工程有限公司",
          "21164:21164|上海之江生物科技有限公司",
          "21175:21175|科美诊断技术股份有限公司",
          "21176:21176|日本希森美康",
          "21177:21177|深圳市亚辉龙生物科技股份有限公司(化学发光)",
          "21192:21192|北京雅康博生物科技有限公司",
          "21193:21193|郑州安图生物工程股份有限公司",
          "21901:21901|DADE",
          "21902:21902|朗道",
          "21903:21903|首医",
          "21904:21904|天津博奥赛斯",
          "21905:21905|科美博阳诊断技术技术（上海）有限公司",
          "21906:21906|四川沃文特生物技术有限公司",
          "21907:21907|厦门万泰凯瑞生物技术有限公司",
          "21908:21908|美康生物",
          "21909:21909|中元汇吉",
          "21910:21910|知微生物（北京）医疗科技有限公司",
          "21911:21911|深圳新产业",
          "21999:21999|其它"
        ]
      },
      {
        "name": "",
        "opts": [
          "21001:21001|上海实业科华生物技术有限公司",
          "21002:21002|华美生物工程公司",
          "21003:21003|厦门新创科技有限公司",
          "21004:21004|上海市传染病医院诊断试剂研制中心",
          "21005:21005|北京科卫临床诊断试剂厂",
          "21006:21006|上海华泰生物工程实业有限公司",
          "21008:21008|北京美迪科生物技术有限责任公司（EIA)",
          "21010:21010|北京北方免疫试剂研究所(EIA)",
          "21011:21011|山东维坊3V诊断技术公司（EIA)",
          "21013:21013|美国贝克曼公司",
          "21015:21015|北京北方生物技术研究所(RIA)",
          "21016:21016|华大GBI生物技术(北京)有限公司",
          "21017:21017|美国万华普曼公司",
          "21018:21018|美国雅培公司（AXSYM)",
          "21019:21019|美国HELIX公司",
          "21020:21020|强生ORTHO 有限公司（ECI）",
          "21021:21021|生物梅里埃",
          "21022:21022|荷兰阿克苏诺贝尔公司",
          "21023:21023|法国赛诺菲公司",
          "21024:21024|上海荣盛生物技术有限公司",
          "21025:21025|美国GENBIO公司",
          "21027:21027|德国欧润",
          "21028:21028|德国埃天郎生物制品有限公司",
          "21029:21029|美国Trinity公司",
          "21030:21030|美国hope",
          "21031:21031|郑州安图绿科生物工程有限公司",
          "21032:21032|深圳华康生物工程有限公司",
          "21033:21033|上海复星实业股份有限公司",
          "21034:21034|天津新传生物技术有限公司",
          "21035:21035|天津普生生物技术有限公司",
          "21036:21036|山东维坊3V生物工程有限公司（RIA）",
          "21037:21037|深圳月亮湾生物工程有限公司",
          "21038:21038|广东中山生物工程公司",
          "21043:21043|丽珠集团公司丽珠试剂厂",
          "21044:21044|福盈生物工程有限公司",
          "21046:21046|北京金豪制药股份有限公司",
          "21050:21050|北京现代高达生物技术有限责任公司",
          "21063:21063|北京新兴四寰生物技术有限公司",
          "21064:21064|深圳迈瑞",
          "21078:21078|达安基因诊断中心",
          "21079:21079|美国BIOCHECK公司",
          "21080:21080|上海复星医学科技发展有限公司（PCR）",
          "21081:21081|北京万泰生物药业有限公司",
          "21082:21082|罗氏（ROCHE）投资有限公司",
          "21083:21083|厦门安普利生物工程公司",
          "21086:21086|上海申友生物技术有限责任公司",
          "21097:21097|深圳匹基生物技术有限公司",
          "21098:21098|广东万孚",
          "21099:21099|欧蒙实验免疫制品有限公司",
          "21105:21105|兰州蓝十字生物技术有限公司",
          "21106:21106|Labsystems公司",
          "21107:21107|意大利索林（SORIN)公司",
          "21108:21108|北京优耐特生物医学有限公司",
          "21109:21109|上海飞龙医用诊断用品公司",
          "21133:21133|北京协和医院",
          "21138:21138|北京金伟凯医学生物技术有限公司",
          "21143:21143|艾康生物技术（杭州）有限公司",
          "21144:21144|苏州新波生物技术有限公司",
          "21147:21147|美国雅培公司（i2000/Alinity i）",
          "21161:21161|湖南圣湘生物科技有限公司",
          "21162:21162|威海威高生物科技有限公司",
          "21163:21163|北京源德生物医学工程有限公司",
          "21164:21164|上海之江生物科技有限公司",
          "21175:21175|科美诊断技术股份有限公司",
          "21176:21176|日本希森美康",
          "21177:21177|深圳市亚辉龙生物科技股份有限公司(化学发光)",
          "21192:21192|北京雅康博生物科技有限公司",
          "21193:21193|郑州安图生物工程股份有限公司",
          "21901:21901|DADE",
          "21902:21902|朗道",
          "21903:21903|首医",
          "21904:21904|天津博奥赛斯",
          "21905:21905|科美博阳诊断技术技术（上海）有限公司",
          "21906:21906|四川沃文特生物技术有限公司",
          "21907:21907|厦门万泰凯瑞生物技术有限公司",
          "21908:21908|美康生物",
          "21909:21909|中元汇吉",
          "21910:21910|知微生物（北京）医疗科技有限公司",
          "21911:21911|深圳新产业",
          "21999:21999|其它"
        ]
      }
    ],
    "headers": []
  },
  "87": {
    "ok": true,
    "rowItems": {
      "0": "8701",
      "1": "87011",
      "2": "8702",
      "3": "87021",
      "4": "8703",
      "5": "-"
    },
    "selects": [
      {
        "name": "",
        "opts": [
          "2101:2101|酶联免疫吸附试验（ELISA）",
          "2102:2102|放射免疫试验（RIA）",
          "2103:2103|间接免疫荧光试验（IFA）",
          "2104:2104|单向(环状)免疫扩散法(SRID)",
          "2105:2105|免疫透射比浊法(ITA)",
          "2106:2106|免疫散射比浊法（INA)",
          "2107:2107|乳胶凝集试验（LA）",
          "2108:2108|免疫渗滤层析试验",
          "2109:2109|快速血浆反应素环状卡片试验(RPR)",
          "2110:2110|不加热血清反应素试验(USR)",
          "2111:2111|螺旋体血球凝集试验(TPHA)",
          "2112:2112|甲苯胺红不加热血清试验(TRUST)",
          "2113:2113|明胶颗粒凝集试验(PA)",
          "2114:2114|荧光偏振免疫试验(FPIA)",
          "2115:2115|时间分辨荧光免疫试验（TR-FIA)",
          "2116:2116|化学发光免疫实验（CLIA）",
          "2117:2117|电化学发光免疫试验（ECLA)",
          "2118:2118|化学发光酶免疫试验（CLEIA）",
          "2119:2119|聚合酶链反应(PCR)",
          "2120:2120|逆转录-聚合酶链反应(RT-PCR)",
          "2121:2121|实时荧光PCR(定量)",
          "2123:2123|转录基于的放大系统(NASBA)",
          "2124:2124|连接酶链反应(LCR)",
          "2125:2125|链替代放大系统(SDA)",
          "2127:2127|bDNA信号放大系统(bDNA)",
          "2128:2128|免疫印记（包括westernblot和RIBA等）",
          "2129:2129|增强化学发光免疫试验",
          "2130:2130|PCR ELISA 定量",
          "2131:2131|PCR ELISA 定性",
          "2133:2133|PCR-反向定点杂交法",
          "2181:2181|透射比浊法",
          "2182:2182|速率散射比浊法",
          "2183:2183|微粒子酶免疫分析",
          "2184:2184|单向（环状）免疫扩散法",
          "2185:2185|散射比浊法（终点法）",
          "2186:2186|免疫印迹",
          "2187:2187|斑点法",
          "2188:2188|酶免疫分析",
          "2189:2189|扫描仪",
          "2190:2190|吖啶酯直接化学发光",
          "2191:2191|光激化学发光",
          "2192:2192|鲁米诺/异鲁米诺化学发光",
          "2199:2199|其它"
        ]
      },
      {
        "name": "",
        "opts": [
          "210000:210000|人眼判断",
          "211001:211001|AW I",
          "211002:211002|AW II",
          "211003:211003|Anthos 2001",
          "211004:211004|Anthos 2010 HT2改成",
          "211005:211005|Anthos HT3",
          "211006:211006|CliniBio 128",
          "211007:211007|CliniBio 128C",
          "211008:211008|DIAS+Vivace",
          "211009:211009|DV-990",
          "211010:211010|DigiScan",
          "211011:211011|EL-309",
          "211012:211012|EL-311",
          "211013:211013|EL-311s",
          "211014:211014|EL-312e",
          "211015:211015|EL-X800G",
          "211016:211016|EL-X800",
          "211017:211017|EL-X808",
          "211018:211018|FAME",
          "211019:211019|LP-400",
          "211020:211020|MR-4100",
          "211021:211021|MR-5000",
          "211022:211022|MRX",
          "211023:211023|MicroReader TM4",
          "211024:211024|Multiskan 352(MK352)",
          "211025:211025|Multiskan II(MK2)",
          "211026:211026|Multiskan III(MK3)",
          "211027:211027|Multiskan Mcc/340",
          "211028:211028|Multiskan Plus",
          "211029:211029|Organon Teknika Micr",
          "211031:211031|STAT FAX-2100",
          "211032:211032|Sigma 960",
          "211033:211033|Spectra Classic",
          "211035:211035|Spectra II",
          "211036:211036|Spectra III",
          "211037:211037|Wellscan",
          "211038:211038|伯乐3500",
          "211039:211039|伯乐3550",
          "211040:211040|伯乐450酶标仪",
          "211041:211041|伯乐550酶标仪",
          "211042:211042|伯乐Coda",
          "211044:211044|华东电子管厂GD-3021",
          "211045:211045|华东电子管厂GD-3022A",
          "211046:211046|Alisei全自动酶免分析仪",
          "211047:211047|普朗DNM9602酶标分析仪",
          "211048:211048|安图2010酶标仪",
          "211049:211049|Labsystem Multisckan Ascent",
          "211050:211050|TECAN Sunrise",
          "211051:211051|AT2000时间分辨检测系统",
          "211052:211052|伯乐680酶标仪",
          "211053:211053|罗氏 ELECSYS 2010",
          "211054:211054|变色龙酶免仪 TRITURUS",
          "211055:211055|宝灵曼ES-700全自动",
          "211056:211056|Anthos 340R",
          "211057:211057|Anthos 340RT",
          "211059:211059|AT-738半自动生化分析仪",
          "211060:211060|AT-838",
          "211061:211061|AFT212 FY1001",
          "211062:211062|ANSR",
          "211063:211063|ET-630G",
          "211064:211064|FG-2008G",
          "211065:211065|FJ-2003/50A",
          "211066:211066|FJ-2008",
          "211067:211067|FJ-2008G",
          "211068:211068|FJ-2008P",
          "211069:211069|FJ-2008PS",
          "211070:211070|FJ-2011",
          "211071:211071|FMJ-180",
          "211072:211072|FMJ-182",
          "211073:211073|FT-613",
          "211074:211074|FT-630G",
          "211075:211075|FT-646A",
          "211076:211076|GAMMA-C12",
          "211077:211077|GC-1200",
          "211078:211078|GC-400",
          "211079:211079|GC-911",
          "211080:211080|ISO-DATA",
          "211081:211081|SN-682",
          "211082:211082|SN-682B",
          "211083:211083|SN-682B2",
          "211084:211084|SN-695",
          "211085:211085|SN-695B",
          "211086:211086|TG-2003",
          "211087:211087|XH-6010",
          "211088:211088|贝克曼CX系列生化分析仪",
          "211089:211089|岛津CL系列生化分析仪",
          "211090:211090|日立 7060，7150，717",
          "211091:211091|意大利BT系列生化分析仪",
          "211092:211092|荷兰ISP系列生化分析仪",
          "211093:211093|Technicon RA50生化分析仪",
          "211094:211094|Technicon RA1000生化仪",
          "211095:211095|721或722型分光光度计",
          "211096:211096|HVK-60免疫比浊仪",
          "211097:211097|ASYS HITECH Gmbh",
          "211099:211099|罗氏 E170",
          "211100:211100|DENLEY DRAGON MK2",
          "211101:211101|DENLEY DRAGON MK3",
          "211102:211102|Bio-Rad iCycle",
          "211103:211103|Bio-Cell 2010",
          "211104:211104|Bio-Cell HT1",
          "211105:211105|Human",
          "211106:211106|Microplate Reader 318,318MC",
          "211107:211107|OPSYS MR CB-372",
          "211108:211108|Personal-LAB",
          "211109:211109|XD-711,711C",
          "211110:211110|XH-711",
          "211111:211111|RT-2100",
          "211112:211112|RT-2100C",
          "211113:211113|V-max",
          "211115:211115|上海新波",
          "211117:211117|Bio-RAD 680",
          "211118:211118|意大利 Alisei",
          "211119:211119|DNM-9602",
          "211120:211120|Emax",
          "211121:211121|BEP-2000",
          "213002:213002|雅培AXSYM 免疫分析仪",
          "213005:213005|Chiron ACS 180SE 全自动酶免分析系统",
          "213006:213006|强生OCD Vitros Eci",
          "213007:213007|雅培i2000/Alinity i",
          "213008:213008|亚斯特Personal LAB 全自动酶免分析仪",
          "213009:213009|亚斯特Nexgen Four 全自动酶免分析仪",
          "213010:213010|上海科华 ST-36W型酶标仪",
          "213019:213019|科美诊断chemclin600全自动化学发光仪",
          "213020:213020|科美诊断chemclin100半自动化学发光仪",
          "213021:213021|科美诊断chemclin1500全自动化学发光免疫分析仪",
          "215001:215001|雷杜RT-6000",
          "215002:215002|雷杜RT-6100",
          "215003:215003|罗氏 Cobas e 411",
          "215004:215004|罗氏 Cobas e 601",
          "215005:215005|HISCL-5000全自动免疫分析仪",
          "215006:215006|HISCL-800全自动免疫分析仪",
          "215007:215007|HISCL-2000i全自动免疫分析仪",
          "215008:215008|罗氏 Cobas e801",
          "217004:217004|OLYMPUS BX（BX50 BX60）显微镜",
          "217008:217008|OLYMPUS其他荧光显微镜",
          "217013:217013|NIKON Fluophoto显微镜",
          "217014:217014|NIKON其他荧光显微镜",
          "217018:217018|其他荧光显微镜",
          "218001:218001|ABI 2400 PCR 仪",
          "218002:218002|ABI 9600 PCR 仪",
          "218003:218003|ABI 9700 PCR 仪",
          "218004:218004|PTC-200 热循环仪",
          "218005:218005|PTC-100 热循环仪",
          "218011:218011|ABI 5700 荧光定量PCR仪",
          "218012:218012|ROCHE Lightcycler",
          "218013:218013|Bio-Rad iCycler",
          "218014:218014|Bio-Rad iCycler 480",
          "218019:218019|ABI 7700 荧光定量PCR仪",
          "218020:218020|ABI 7000 荧光定量PCR仪",
          "218021:218021|ABI 7900 荧光定量PCR仪",
          "218022:218022|COBAS AMPLICOR",
          "218023:218023|COBAS TaqMan",
          "218024:218024|ABI 7300 荧光定量PCR仪",
          "218025:218025|ABI 7500 荧光定量PCR仪",
          "218026:218026|Rotor Gene",
          "218027:218027|Line-Gene",
          "218028:218028|MJ Research Opticon II",
          "218029:218029|FTC 2000",
          "218030:218030|DA7600核酸扩增实时荧光检测系统",
          "218031:218031|科华FluoCycle 实时荧光定量PCR仪",
          "218032:218032|SLAN荧光定量PCR仪",
          "218099:218099|其它PCR仪",
          "218100:218100|医用核酸分子快速杂交仪HHM-2",
          "218101:218101|Luminex 100",
          "218102:218102|Luminex 200",
          "218103:218103|AM-1型全自动自身抗体分析仪",
          "218104:218104|EM-1型感染免疫分析仪",
          "218105:218105|Genelight 9800全自动医用PCR分析系统",
          "218106:218106|Genelight 2400全自动医用PCR分析系统",
          "218107:218107|伯乐CFX96实时定量PCR仪",
          "218108:218108|Liaison化学发光分析仪",
          "218109:218109|MiniVIDAS BLUE",
          "218110:218110|VIDAS 30 BLUE",
          "218111:218111|Auto lumiS 2000",
          "218112:218112|Auto lumiS 3000",
          "218113:218113|ADC ELISA",
          "218114:218114|迈克IS 1200全自动化学发光测定仪",
          "218115:218115|迈克i1000全自动化学发光测定仪",
          "218116:218116|迈克i3000全自动化学发光测定仪",
          "219010:219010|Beckman IMMAGE",
          "219020:219020|Dade Behring BNP",
          "219030:219030|Olympus AU2700",
          "219040:219040|欧蒙Scall",
          "219041:219041|欧蒙BX-51",
          "219042:219042|深圳迈瑞CL-900i/1000i/1200i/2000i/2200i/6000i/6200",
          "2190421:2190421|深圳迈瑞CL-8000i",
          "219043:219043|安图AutoLumo A2000",
          "219044:219044|安图AutoLumo A2000 Plus",
          "219045:219045|博奥赛斯（天津） Peteck 96-I",
          "219046:219046|博奥赛斯（天津） Axceed 200T/400T",
          "219047:219047|博奥赛斯（天津） Axceed 260/260X/260X1",
          "219048:219048|亚辉龙iFlash3000系列化学发光测定仪",
          "219049:219049|科美博阳LICA 500/LICA800/LICAsmart全自动化学发光仪",
          "219050:219050|日立",
          "219051:219051|四川沃文特LA3000/LA3000S",
          "219052:219052|厦门优迈科Caris200/Wan200/Wan100",
          "219053:219053|美康MS-i2280/3080",
          "219054:219054|中元汇吉EXI2400/8000",
          "219055:219055|深圳迈瑞 CL-9000i/9200i",
          "219056:219056|知微知微生物全自动核酸扩增分析仪（型号NAT-3000)",
          "219057:219057|知微生物全自动核酸扩增分析仪（型号NAT-3000 Pro-4)",
          "219058:219058|知微生物全自动核酸扩增分析仪（型号NAT-3000 Pro-8)",
          "219059:219059|知微生物全自动核酸扩增分析仪（型号NAT-3000 Pro-12)",
          "219060:219060|知微生物全自动核酸扩增分析仪（型号NAT-3000 Pro-16)",
          "219061:219061|新产业 Maglumi 全自动化学发光测定仪系列",
          "219999:219999|其它",
          "251003:251003|雷杜RT-2100C"
        ]
      },
      {
        "name": "",
        "opts": [
          "21001:21001|上海实业科华生物技术有限公司",
          "21002:21002|华美生物工程公司",
          "21003:21003|厦门新创科技有限公司",
          "21004:21004|上海市传染病医院诊断试剂研制中心",
          "21005:21005|北京科卫临床诊断试剂厂",
          "21006:21006|上海华泰生物工程实业有限公司",
          "21008:21008|北京美迪科生物技术有限责任公司（EIA)",
          "21010:21010|北京北方免疫试剂研究所(EIA)",
          "21011:21011|山东维坊3V诊断技术公司（EIA)",
          "21013:21013|美国贝克曼公司",
          "21015:21015|北京北方生物技术研究所(RIA)",
          "21016:21016|华大GBI生物技术(北京)有限公司",
          "21017:21017|美国万华普曼公司",
          "21018:21018|美国雅培公司（AXSYM)",
          "21019:21019|美国HELIX公司",
          "21020:21020|强生ORTHO 有限公司（ECI）",
          "21021:21021|生物梅里埃",
          "21022:21022|荷兰阿克苏诺贝尔公司",
          "21023:21023|法国赛诺菲公司",
          "21024:21024|上海荣盛生物技术有限公司",
          "21025:21025|美国GENBIO公司",
          "21027:21027|德国欧润",
          "21028:21028|德国埃天郎生物制品有限公司",
          "21029:21029|美国Trinity公司",
          "21030:21030|美国hope",
          "21031:21031|郑州安图绿科生物工程有限公司",
          "21032:21032|深圳华康生物工程有限公司",
          "21033:21033|上海复星实业股份有限公司",
          "21034:21034|天津新传生物技术有限公司",
          "21035:21035|天津普生生物技术有限公司",
          "21036:21036|山东维坊3V生物工程有限公司（RIA）",
          "21037:21037|深圳月亮湾生物工程有限公司",
          "21038:21038|广东中山生物工程公司",
          "21043:21043|丽珠集团公司丽珠试剂厂",
          "21044:21044|福盈生物工程有限公司",
          "21046:21046|北京金豪制药股份有限公司",
          "21050:21050|北京现代高达生物技术有限责任公司",
          "21063:21063|北京新兴四寰生物技术有限公司",
          "21064:21064|深圳迈瑞",
          "21078:21078|达安基因诊断中心",
          "21079:21079|美国BIOCHECK公司",
          "21080:21080|上海复星医学科技发展有限公司（PCR）",
          "21081:21081|北京万泰生物药业有限公司",
          "21082:21082|罗氏（ROCHE）投资有限公司",
          "21083:21083|厦门安普利生物工程公司",
          "21086:21086|上海申友生物技术有限责任公司",
          "21097:21097|深圳匹基生物技术有限公司",
          "21098:21098|广东万孚",
          "21099:21099|欧蒙实验免疫制品有限公司",
          "21105:21105|兰州蓝十字生物技术有限公司",
          "21106:21106|Labsystems公司",
          "21107:21107|意大利索林（SORIN)公司",
          "21108:21108|北京优耐特生物医学有限公司",
          "21109:21109|上海飞龙医用诊断用品公司",
          "21133:21133|北京协和医院",
          "21138:21138|北京金伟凯医学生物技术有限公司",
          "21143:21143|艾康生物技术（杭州）有限公司",
          "21144:21144|苏州新波生物技术有限公司",
          "21147:21147|美国雅培公司（i2000/Alinity i）",
          "21161:21161|湖南圣湘生物科技有限公司",
          "21162:21162|威海威高生物科技有限公司",
          "21163:21163|北京源德生物医学工程有限公司",
          "21164:21164|上海之江生物科技有限公司",
          "21175:21175|科美诊断技术股份有限公司",
          "21176:21176|日本希森美康",
          "21177:21177|深圳市亚辉龙生物科技股份有限公司(化学发光)",
          "21192:21192|北京雅康博生物科技有限公司",
          "21193:21193|郑州安图生物工程股份有限公司",
          "21901:21901|DADE",
          "21902:21902|朗道",
          "21903:21903|首医",
          "21904:21904|天津博奥赛斯",
          "21905:21905|科美博阳诊断技术技术（上海）有限公司",
          "21906:21906|四川沃文特生物技术有限公司",
          "21907:21907|厦门万泰凯瑞生物技术有限公司",
          "21908:21908|美康生物",
          "21909:21909|中元汇吉",
          "21910:21910|知微生物（北京）医疗科技有限公司",
          "21911:21911|深圳新产业",
          "21999:21999|其它"
        ]
      },
      {
        "name": "",
        "opts": [
          "21001:21001|上海实业科华生物技术有限公司",
          "21002:21002|华美生物工程公司",
          "21003:21003|厦门新创科技有限公司",
          "21004:21004|上海市传染病医院诊断试剂研制中心",
          "21005:21005|北京科卫临床诊断试剂厂",
          "21006:21006|上海华泰生物工程实业有限公司",
          "21008:21008|北京美迪科生物技术有限责任公司（EIA)",
          "21010:21010|北京北方免疫试剂研究所(EIA)",
          "21011:21011|山东维坊3V诊断技术公司（EIA)",
          "21013:21013|美国贝克曼公司",
          "21015:21015|北京北方生物技术研究所(RIA)",
          "21016:21016|华大GBI生物技术(北京)有限公司",
          "21017:21017|美国万华普曼公司",
          "21018:21018|美国雅培公司（AXSYM)",
          "21019:21019|美国HELIX公司",
          "21020:21020|强生ORTHO 有限公司（ECI）",
          "21021:21021|生物梅里埃",
          "21022:21022|荷兰阿克苏诺贝尔公司",
          "21023:21023|法国赛诺菲公司",
          "21024:21024|上海荣盛生物技术有限公司",
          "21025:21025|美国GENBIO公司",
          "21027:21027|德国欧润",
          "21028:21028|德国埃天郎生物制品有限公司",
          "21029:21029|美国Trinity公司",
          "21030:21030|美国hope",
          "21031:21031|郑州安图绿科生物工程有限公司",
          "21032:21032|深圳华康生物工程有限公司",
          "21033:21033|上海复星实业股份有限公司",
          "21034:21034|天津新传生物技术有限公司",
          "21035:21035|天津普生生物技术有限公司",
          "21036:21036|山东维坊3V生物工程有限公司（RIA）",
          "21037:21037|深圳月亮湾生物工程有限公司",
          "21038:21038|广东中山生物工程公司",
          "21043:21043|丽珠集团公司丽珠试剂厂",
          "21044:21044|福盈生物工程有限公司",
          "21046:21046|北京金豪制药股份有限公司",
          "21050:21050|北京现代高达生物技术有限责任公司",
          "21063:21063|北京新兴四寰生物技术有限公司",
          "21064:21064|深圳迈瑞",
          "21078:21078|达安基因诊断中心",
          "21079:21079|美国BIOCHECK公司",
          "21080:21080|上海复星医学科技发展有限公司（PCR）",
          "21081:21081|北京万泰生物药业有限公司",
          "21082:21082|罗氏（ROCHE）投资有限公司",
          "21083:21083|厦门安普利生物工程公司",
          "21086:21086|上海申友生物技术有限责任公司",
          "21097:21097|深圳匹基生物技术有限公司",
          "21098:21098|广东万孚",
          "21099:21099|欧蒙实验免疫制品有限公司",
          "21105:21105|兰州蓝十字生物技术有限公司",
          "21106:21106|Labsystems公司",
          "21107:21107|意大利索林（SORIN)公司",
          "21108:21108|北京优耐特生物医学有限公司",
          "21109:21109|上海飞龙医用诊断用品公司",
          "21133:21133|北京协和医院",
          "21138:21138|北京金伟凯医学生物技术有限公司",
          "21143:21143|艾康生物技术（杭州）有限公司",
          "21144:21144|苏州新波生物技术有限公司",
          "21147:21147|美国雅培公司（i2000/Alinity i）",
          "21161:21161|湖南圣湘生物科技有限公司",
          "21162:21162|威海威高生物科技有限公司",
          "21163:21163|北京源德生物医学工程有限公司",
          "21164:21164|上海之江生物科技有限公司",
          "21175:21175|科美诊断技术股份有限公司",
          "21176:21176|日本希森美康",
          "21177:21177|深圳市亚辉龙生物科技股份有限公司(化学发光)",
          "21192:21192|北京雅康博生物科技有限公司",
          "21193:21193|郑州安图生物工程股份有限公司",
          "21901:21901|DADE",
          "21902:21902|朗道",
          "21903:21903|首医",
          "21904:21904|天津博奥赛斯",
          "21905:21905|科美博阳诊断技术技术（上海）有限公司",
          "21906:21906|四川沃文特生物技术有限公司",
          "21907:21907|厦门万泰凯瑞生物技术有限公司",
          "21908:21908|美康生物",
          "21909:21909|中元汇吉",
          "21910:21910|知微生物（北京）医疗科技有限公司",
          "21911:21911|深圳新产业",
          "21999:21999|其它"
        ]
      }
    ],
    "headers": []
  },
  "88": {
    "ok": true,
    "rowItems": {
      "0": "8801",
      "1": "8802",
      "2": "8803",
      "3": "8804",
      "4": "-"
    },
    "selects": [
      {
        "name": "",
        "opts": [
          "2101:2101|酶联免疫吸附试验（ELISA）",
          "2102:2102|放射免疫试验（RIA）",
          "2103:2103|间接免疫荧光试验（IFA）",
          "2104:2104|单向(环状)免疫扩散法(SRID)",
          "2105:2105|免疫透射比浊法(ITA)",
          "2106:2106|免疫散射比浊法（INA)",
          "2107:2107|乳胶凝集试验（LA）",
          "2108:2108|免疫渗滤层析试验",
          "2109:2109|快速血浆反应素环状卡片试验(RPR)",
          "2110:2110|不加热血清反应素试验(USR)",
          "2111:2111|螺旋体血球凝集试验(TPHA)",
          "2112:2112|甲苯胺红不加热血清试验(TRUST)",
          "2113:2113|明胶颗粒凝集试验(PA)",
          "2114:2114|荧光偏振免疫试验(FPIA)",
          "2115:2115|时间分辨荧光免疫试验（TR-FIA)",
          "2116:2116|化学发光免疫实验（CLIA）",
          "2117:2117|电化学发光免疫试验（ECLA)",
          "2118:2118|化学发光酶免疫试验（CLEIA）",
          "2119:2119|聚合酶链反应(PCR)",
          "2120:2120|逆转录-聚合酶链反应(RT-PCR)",
          "2121:2121|实时荧光PCR(定量)",
          "2123:2123|转录基于的放大系统(NASBA)",
          "2124:2124|连接酶链反应(LCR)",
          "2125:2125|链替代放大系统(SDA)",
          "2127:2127|bDNA信号放大系统(bDNA)",
          "2128:2128|免疫印记（包括westernblot和RIBA等）",
          "2129:2129|增强化学发光免疫试验",
          "2130:2130|PCR ELISA 定量",
          "2131:2131|PCR ELISA 定性",
          "2133:2133|PCR-反向定点杂交法",
          "2181:2181|透射比浊法",
          "2182:2182|速率散射比浊法",
          "2183:2183|微粒子酶免疫分析",
          "2184:2184|单向（环状）免疫扩散法",
          "2185:2185|散射比浊法（终点法）",
          "2186:2186|免疫印迹",
          "2187:2187|斑点法",
          "2188:2188|酶免疫分析",
          "2189:2189|扫描仪",
          "2190:2190|吖啶酯直接化学发光",
          "2191:2191|光激化学发光",
          "2192:2192|鲁米诺/异鲁米诺化学发光",
          "2199:2199|其它"
        ]
      },
      {
        "name": "",
        "opts": [
          "210000:210000|人眼判断",
          "211001:211001|AW I",
          "211002:211002|AW II",
          "211003:211003|Anthos 2001",
          "211004:211004|Anthos 2010 HT2改成",
          "211005:211005|Anthos HT3",
          "211006:211006|CliniBio 128",
          "211007:211007|CliniBio 128C",
          "211008:211008|DIAS+Vivace",
          "211009:211009|DV-990",
          "211010:211010|DigiScan",
          "211011:211011|EL-309",
          "211012:211012|EL-311",
          "211013:211013|EL-311s",
          "211014:211014|EL-312e",
          "211015:211015|EL-X800G",
          "211016:211016|EL-X800",
          "211017:211017|EL-X808",
          "211018:211018|FAME",
          "211019:211019|LP-400",
          "211020:211020|MR-4100",
          "211021:211021|MR-5000",
          "211022:211022|MRX",
          "211023:211023|MicroReader TM4",
          "211024:211024|Multiskan 352(MK352)",
          "211025:211025|Multiskan II(MK2)",
          "211026:211026|Multiskan III(MK3)",
          "211027:211027|Multiskan Mcc/340",
          "211028:211028|Multiskan Plus",
          "211029:211029|Organon Teknika Micr",
          "211031:211031|STAT FAX-2100",
          "211032:211032|Sigma 960",
          "211033:211033|Spectra Classic",
          "211035:211035|Spectra II",
          "211036:211036|Spectra III",
          "211037:211037|Wellscan",
          "211038:211038|伯乐3500",
          "211039:211039|伯乐3550",
          "211040:211040|伯乐450酶标仪",
          "211041:211041|伯乐550酶标仪",
          "211042:211042|伯乐Coda",
          "211044:211044|华东电子管厂GD-3021",
          "211045:211045|华东电子管厂GD-3022A",
          "211046:211046|Alisei全自动酶免分析仪",
          "211047:211047|普朗DNM9602酶标分析仪",
          "211048:211048|安图2010酶标仪",
          "211049:211049|Labsystem Multisckan Ascent",
          "211050:211050|TECAN Sunrise",
          "211051:211051|AT2000时间分辨检测系统",
          "211052:211052|伯乐680酶标仪",
          "211053:211053|罗氏 ELECSYS 2010",
          "211054:211054|变色龙酶免仪 TRITURUS",
          "211055:211055|宝灵曼ES-700全自动",
          "211056:211056|Anthos 340R",
          "211057:211057|Anthos 340RT",
          "211059:211059|AT-738半自动生化分析仪",
          "211060:211060|AT-838",
          "211061:211061|AFT212 FY1001",
          "211062:211062|ANSR",
          "211063:211063|ET-630G",
          "211064:211064|FG-2008G",
          "211065:211065|FJ-2003/50A",
          "211066:211066|FJ-2008",
          "211067:211067|FJ-2008G",
          "211068:211068|FJ-2008P",
          "211069:211069|FJ-2008PS",
          "211070:211070|FJ-2011",
          "211071:211071|FMJ-180",
          "211072:211072|FMJ-182",
          "211073:211073|FT-613",
          "211074:211074|FT-630G",
          "211075:211075|FT-646A",
          "211076:211076|GAMMA-C12",
          "211077:211077|GC-1200",
          "211078:211078|GC-400",
          "211079:211079|GC-911",
          "211080:211080|ISO-DATA",
          "211081:211081|SN-682",
          "211082:211082|SN-682B",
          "211083:211083|SN-682B2",
          "211084:211084|SN-695",
          "211085:211085|SN-695B",
          "211086:211086|TG-2003",
          "211087:211087|XH-6010",
          "211088:211088|贝克曼CX系列生化分析仪",
          "211089:211089|岛津CL系列生化分析仪",
          "211090:211090|日立 7060，7150，717",
          "211091:211091|意大利BT系列生化分析仪",
          "211092:211092|荷兰ISP系列生化分析仪",
          "211093:211093|Technicon RA50生化分析仪",
          "211094:211094|Technicon RA1000生化仪",
          "211095:211095|721或722型分光光度计",
          "211096:211096|HVK-60免疫比浊仪",
          "211097:211097|ASYS HITECH Gmbh",
          "211099:211099|罗氏 E170",
          "211100:211100|DENLEY DRAGON MK2",
          "211101:211101|DENLEY DRAGON MK3",
          "211102:211102|Bio-Rad iCycle",
          "211103:211103|Bio-Cell 2010",
          "211104:211104|Bio-Cell HT1",
          "211105:211105|Human",
          "211106:211106|Microplate Reader 318,318MC",
          "211107:211107|OPSYS MR CB-372",
          "211108:211108|Personal-LAB",
          "211109:211109|XD-711,711C",
          "211110:211110|XH-711",
          "211111:211111|RT-2100",
          "211112:211112|RT-2100C",
          "211113:211113|V-max",
          "211115:211115|上海新波",
          "211117:211117|Bio-RAD 680",
          "211118:211118|意大利 Alisei",
          "211119:211119|DNM-9602",
          "211120:211120|Emax",
          "211121:211121|BEP-2000",
          "213002:213002|雅培AXSYM 免疫分析仪",
          "213005:213005|Chiron ACS 180SE 全自动酶免分析系统",
          "213006:213006|强生OCD Vitros Eci",
          "213007:213007|雅培i2000/Alinity i",
          "213008:213008|亚斯特Personal LAB 全自动酶免分析仪",
          "213009:213009|亚斯特Nexgen Four 全自动酶免分析仪",
          "213010:213010|上海科华 ST-36W型酶标仪",
          "213019:213019|科美诊断chemclin600全自动化学发光仪",
          "213020:213020|科美诊断chemclin100半自动化学发光仪",
          "213021:213021|科美诊断chemclin1500全自动化学发光免疫分析仪",
          "215001:215001|雷杜RT-6000",
          "215002:215002|雷杜RT-6100",
          "215003:215003|罗氏 Cobas e 411",
          "215004:215004|罗氏 Cobas e 601",
          "215005:215005|HISCL-5000全自动免疫分析仪",
          "215006:215006|HISCL-800全自动免疫分析仪",
          "215007:215007|HISCL-2000i全自动免疫分析仪",
          "215008:215008|罗氏 Cobas e801",
          "217004:217004|OLYMPUS BX（BX50 BX60）显微镜",
          "217008:217008|OLYMPUS其他荧光显微镜",
          "217013:217013|NIKON Fluophoto显微镜",
          "217014:217014|NIKON其他荧光显微镜",
          "217018:217018|其他荧光显微镜",
          "218001:218001|ABI 2400 PCR 仪",
          "218002:218002|ABI 9600 PCR 仪",
          "218003:218003|ABI 9700 PCR 仪",
          "218004:218004|PTC-200 热循环仪",
          "218005:218005|PTC-100 热循环仪",
          "218011:218011|ABI 5700 荧光定量PCR仪",
          "218012:218012|ROCHE Lightcycler",
          "218013:218013|Bio-Rad iCycler",
          "218014:218014|Bio-Rad iCycler 480",
          "218019:218019|ABI 7700 荧光定量PCR仪",
          "218020:218020|ABI 7000 荧光定量PCR仪",
          "218021:218021|ABI 7900 荧光定量PCR仪",
          "218022:218022|COBAS AMPLICOR",
          "218023:218023|COBAS TaqMan",
          "218024:218024|ABI 7300 荧光定量PCR仪",
          "218025:218025|ABI 7500 荧光定量PCR仪",
          "218026:218026|Rotor Gene",
          "218027:218027|Line-Gene",
          "218028:218028|MJ Research Opticon II",
          "218029:218029|FTC 2000",
          "218030:218030|DA7600核酸扩增实时荧光检测系统",
          "218031:218031|科华FluoCycle 实时荧光定量PCR仪",
          "218032:218032|SLAN荧光定量PCR仪",
          "218099:218099|其它PCR仪",
          "218100:218100|医用核酸分子快速杂交仪HHM-2",
          "218101:218101|Luminex 100",
          "218102:218102|Luminex 200",
          "218103:218103|AM-1型全自动自身抗体分析仪",
          "218104:218104|EM-1型感染免疫分析仪",
          "218105:218105|Genelight 9800全自动医用PCR分析系统",
          "218106:218106|Genelight 2400全自动医用PCR分析系统",
          "218107:218107|伯乐CFX96实时定量PCR仪",
          "218108:218108|Liaison化学发光分析仪",
          "218109:218109|MiniVIDAS BLUE",
          "218110:218110|VIDAS 30 BLUE",
          "218111:218111|Auto lumiS 2000",
          "218112:218112|Auto lumiS 3000",
          "218113:218113|ADC ELISA",
          "218114:218114|迈克IS 1200全自动化学发光测定仪",
          "218115:218115|迈克i1000全自动化学发光测定仪",
          "218116:218116|迈克i3000全自动化学发光测定仪",
          "219010:219010|Beckman IMMAGE",
          "219020:219020|Dade Behring BNP",
          "219030:219030|Olympus AU2700",
          "219040:219040|欧蒙Scall",
          "219041:219041|欧蒙BX-51",
          "219042:219042|深圳迈瑞CL-900i/1000i/1200i/2000i/2200i/6000i/6200",
          "2190421:2190421|深圳迈瑞CL-8000i",
          "219043:219043|安图AutoLumo A2000",
          "219044:219044|安图AutoLumo A2000 Plus",
          "219045:219045|博奥赛斯（天津） Peteck 96-I",
          "219046:219046|博奥赛斯（天津） Axceed 200T/400T",
          "219047:219047|博奥赛斯（天津） Axceed 260/260X/260X1",
          "219048:219048|亚辉龙iFlash3000系列化学发光测定仪",
          "219049:219049|科美博阳LICA 500/LICA800/LICAsmart全自动化学发光仪",
          "219050:219050|日立",
          "219051:219051|四川沃文特LA3000/LA3000S",
          "219052:219052|厦门优迈科Caris200/Wan200/Wan100",
          "219053:219053|美康MS-i2280/3080",
          "219054:219054|中元汇吉EXI2400/8000",
          "219055:219055|深圳迈瑞 CL-9000i/9200i",
          "219056:219056|知微知微生物全自动核酸扩增分析仪（型号NAT-3000)",
          "219057:219057|知微生物全自动核酸扩增分析仪（型号NAT-3000 Pro-4)",
          "219058:219058|知微生物全自动核酸扩增分析仪（型号NAT-3000 Pro-8)",
          "219059:219059|知微生物全自动核酸扩增分析仪（型号NAT-3000 Pro-12)",
          "219060:219060|知微生物全自动核酸扩增分析仪（型号NAT-3000 Pro-16)",
          "219061:219061|新产业 Maglumi 全自动化学发光测定仪系列",
          "219999:219999|其它",
          "251003:251003|雷杜RT-2100C"
        ]
      },
      {
        "name": "",
        "opts": [
          "21001:21001|上海实业科华生物技术有限公司",
          "21002:21002|华美生物工程公司",
          "21003:21003|厦门新创科技有限公司",
          "21004:21004|上海市传染病医院诊断试剂研制中心",
          "21005:21005|北京科卫临床诊断试剂厂",
          "21006:21006|上海华泰生物工程实业有限公司",
          "21008:21008|北京美迪科生物技术有限责任公司（EIA)",
          "21010:21010|北京北方免疫试剂研究所(EIA)",
          "21011:21011|山东维坊3V诊断技术公司（EIA)",
          "21013:21013|美国贝克曼公司",
          "21015:21015|北京北方生物技术研究所(RIA)",
          "21016:21016|华大GBI生物技术(北京)有限公司",
          "21017:21017|美国万华普曼公司",
          "21018:21018|美国雅培公司（AXSYM)",
          "21019:21019|美国HELIX公司",
          "21020:21020|强生ORTHO 有限公司（ECI）",
          "21021:21021|生物梅里埃",
          "21022:21022|荷兰阿克苏诺贝尔公司",
          "21023:21023|法国赛诺菲公司",
          "21024:21024|上海荣盛生物技术有限公司",
          "21025:21025|美国GENBIO公司",
          "21027:21027|德国欧润",
          "21028:21028|德国埃天郎生物制品有限公司",
          "21029:21029|美国Trinity公司",
          "21030:21030|美国hope",
          "21031:21031|郑州安图绿科生物工程有限公司",
          "21032:21032|深圳华康生物工程有限公司",
          "21033:21033|上海复星实业股份有限公司",
          "21034:21034|天津新传生物技术有限公司",
          "21035:21035|天津普生生物技术有限公司",
          "21036:21036|山东维坊3V生物工程有限公司（RIA）",
          "21037:21037|深圳月亮湾生物工程有限公司",
          "21038:21038|广东中山生物工程公司",
          "21043:21043|丽珠集团公司丽珠试剂厂",
          "21044:21044|福盈生物工程有限公司",
          "21046:21046|北京金豪制药股份有限公司",
          "21050:21050|北京现代高达生物技术有限责任公司",
          "21063:21063|北京新兴四寰生物技术有限公司",
          "21064:21064|深圳迈瑞",
          "21078:21078|达安基因诊断中心",
          "21079:21079|美国BIOCHECK公司",
          "21080:21080|上海复星医学科技发展有限公司（PCR）",
          "21081:21081|北京万泰生物药业有限公司",
          "21082:21082|罗氏（ROCHE）投资有限公司",
          "21083:21083|厦门安普利生物工程公司",
          "21086:21086|上海申友生物技术有限责任公司",
          "21097:21097|深圳匹基生物技术有限公司",
          "21098:21098|广东万孚",
          "21099:21099|欧蒙实验免疫制品有限公司",
          "21105:21105|兰州蓝十字生物技术有限公司",
          "21106:21106|Labsystems公司",
          "21107:21107|意大利索林（SORIN)公司",
          "21108:21108|北京优耐特生物医学有限公司",
          "21109:21109|上海飞龙医用诊断用品公司",
          "21133:21133|北京协和医院",
          "21138:21138|北京金伟凯医学生物技术有限公司",
          "21143:21143|艾康生物技术（杭州）有限公司",
          "21144:21144|苏州新波生物技术有限公司",
          "21147:21147|美国雅培公司（i2000/Alinity i）",
          "21161:21161|湖南圣湘生物科技有限公司",
          "21162:21162|威海威高生物科技有限公司",
          "21163:21163|北京源德生物医学工程有限公司",
          "21164:21164|上海之江生物科技有限公司",
          "21175:21175|科美诊断技术股份有限公司",
          "21176:21176|日本希森美康",
          "21177:21177|深圳市亚辉龙生物科技股份有限公司(化学发光)",
          "21192:21192|北京雅康博生物科技有限公司",
          "21193:21193|郑州安图生物工程股份有限公司",
          "21901:21901|DADE",
          "21902:21902|朗道",
          "21903:21903|首医",
          "21904:21904|天津博奥赛斯",
          "21905:21905|科美博阳诊断技术技术（上海）有限公司",
          "21906:21906|四川沃文特生物技术有限公司",
          "21907:21907|厦门万泰凯瑞生物技术有限公司",
          "21908:21908|美康生物",
          "21909:21909|中元汇吉",
          "21910:21910|知微生物（北京）医疗科技有限公司",
          "21911:21911|深圳新产业",
          "21999:21999|其它"
        ]
      },
      {
        "name": "",
        "opts": [
          "21001:21001|上海实业科华生物技术有限公司",
          "21002:21002|华美生物工程公司",
          "21003:21003|厦门新创科技有限公司",
          "21004:21004|上海市传染病医院诊断试剂研制中心",
          "21005:21005|北京科卫临床诊断试剂厂",
          "21006:21006|上海华泰生物工程实业有限公司",
          "21008:21008|北京美迪科生物技术有限责任公司（EIA)",
          "21010:21010|北京北方免疫试剂研究所(EIA)",
          "21011:21011|山东维坊3V诊断技术公司（EIA)",
          "21013:21013|美国贝克曼公司",
          "21015:21015|北京北方生物技术研究所(RIA)",
          "21016:21016|华大GBI生物技术(北京)有限公司",
          "21017:21017|美国万华普曼公司",
          "21018:21018|美国雅培公司（AXSYM)",
          "21019:21019|美国HELIX公司",
          "21020:21020|强生ORTHO 有限公司（ECI）",
          "21021:21021|生物梅里埃",
          "21022:21022|荷兰阿克苏诺贝尔公司",
          "21023:21023|法国赛诺菲公司",
          "21024:21024|上海荣盛生物技术有限公司",
          "21025:21025|美国GENBIO公司",
          "21027:21027|德国欧润",
          "21028:21028|德国埃天郎生物制品有限公司",
          "21029:21029|美国Trinity公司",
          "21030:21030|美国hope",
          "21031:21031|郑州安图绿科生物工程有限公司",
          "21032:21032|深圳华康生物工程有限公司",
          "21033:21033|上海复星实业股份有限公司",
          "21034:21034|天津新传生物技术有限公司",
          "21035:21035|天津普生生物技术有限公司",
          "21036:21036|山东维坊3V生物工程有限公司（RIA）",
          "21037:21037|深圳月亮湾生物工程有限公司",
          "21038:21038|广东中山生物工程公司",
          "21043:21043|丽珠集团公司丽珠试剂厂",
          "21044:21044|福盈生物工程有限公司",
          "21046:21046|北京金豪制药股份有限公司",
          "21050:21050|北京现代高达生物技术有限责任公司",
          "21063:21063|北京新兴四寰生物技术有限公司",
          "21064:21064|深圳迈瑞",
          "21078:21078|达安基因诊断中心",
          "21079:21079|美国BIOCHECK公司",
          "21080:21080|上海复星医学科技发展有限公司（PCR）",
          "21081:21081|北京万泰生物药业有限公司",
          "21082:21082|罗氏（ROCHE）投资有限公司",
          "21083:21083|厦门安普利生物工程公司",
          "21086:21086|上海申友生物技术有限责任公司",
          "21097:21097|深圳匹基生物技术有限公司",
          "21098:21098|广东万孚",
          "21099:21099|欧蒙实验免疫制品有限公司",
          "21105:21105|兰州蓝十字生物技术有限公司",
          "21106:21106|Labsystems公司",
          "21107:21107|意大利索林（SORIN)公司",
          "21108:21108|北京优耐特生物医学有限公司",
          "21109:21109|上海飞龙医用诊断用品公司",
          "21133:21133|北京协和医院",
          "21138:21138|北京金伟凯医学生物技术有限公司",
          "21143:21143|艾康生物技术（杭州）有限公司",
          "21144:21144|苏州新波生物技术有限公司",
          "21147:21147|美国雅培公司（i2000/Alinity i）",
          "21161:21161|湖南圣湘生物科技有限公司",
          "21162:21162|威海威高生物科技有限公司",
          "21163:21163|北京源德生物医学工程有限公司",
          "21164:21164|上海之江生物科技有限公司",
          "21175:21175|科美诊断技术股份有限公司",
          "21176:21176|日本希森美康",
          "21177:21177|深圳市亚辉龙生物科技股份有限公司(化学发光)",
          "21192:21192|北京雅康博生物科技有限公司",
          "21193:21193|郑州安图生物工程股份有限公司",
          "21901:21901|DADE",
          "21902:21902|朗道",
          "21903:21903|首医",
          "21904:21904|天津博奥赛斯",
          "21905:21905|科美博阳诊断技术技术（上海）有限公司",
          "21906:21906|四川沃文特生物技术有限公司",
          "21907:21907|厦门万泰凯瑞生物技术有限公司",
          "21908:21908|美康生物",
          "21909:21909|中元汇吉",
          "21910:21910|知微生物（北京）医疗科技有限公司",
          "21911:21911|深圳新产业",
          "21999:21999|其它"
        ]
      }
    ],
    "headers": []
  }
}